<xml xmlns="http://www.w3.org/1999/xhtml"><variables><variable type="" id="x0J?+0Rdk2z1=BDG6A/D">sheep</variable></variables><block type="onchat" id="!%KYU?,cYDd)(M8*((UR" x="115" y="108"><value name="command"><block type="text" id="x7uF[JvMc/q+B!zBeV}N"><field name="TEXT">sheepDye</field></block></value><statement name="statements"><block type="event_playerentity" id="|Z}hg;P/v+GH_`NYHc}`"><statement name="ENTITY"><block type="controls_try" id="@~b?}~CU}`1%gT3SNu9f"><statement name="TRY"><block type="variables_set" id="OsD,%B:WhUSHLcbMjt3p"><field name="VAR" id="x0J?+0Rdk2z1=BDG6A/D" variabletype="">sheep</field><value name="VALUE"><block type="entity_rightclick" id="CfEcaXT+9g9Gn6PN)Pqb"><comment pinned="false" h="80" w="160">개체 상호작용 이벤트 필요</comment></block></value><next><block type="dye_color" id="i8:-XQcOqjd^LB(=3fv["><value name="ENTITY"><block type="variables_get" id="PN%[2l;O}J[0dsnaIKc%"><field name="VAR" id="x0J?+0Rdk2z1=BDG6A/D" variabletype="">sheep</field></block></value><value name="COLOR"><block type="colors_var" id="*$X)/I!W*;o5V=2J0h]N"><field name="COLOR">RED</field></block></value></block></next></block></statement><statement name="CATCH"><block type="player_chat" id="rS;n+~Sx`6S/9(#WPJP$"><value name="chat"><block type="text" id="|Mhai|t~@RnLu~N.{$MA"><field name="TEXT">해당 개체는 양이 아닙니다.</field></block></value></block></statement></block></statement></block></statement></block></xml>